orderly_set/__init__.py
orderly_set/py.typed
orderly_set/sets.py
orderly_set-5.3.2.dist-info/AUTHORS.md
orderly_set-5.3.2.dist-info/METADATA
orderly_set-5.3.2.dist-info/WHEEL
orderly_set-5.3.2.dist-info/top_level.txt
orderly_set-5.3.2.dist-info/zip-safe
orderly_set-5.3.2.dist-info/RECORD
